{
    "url": "https://support.google.com/pixelphone/thread/47531444/when-i-insert-orders-to-the-routines-in-the-google-assistant-he-does-not-do-the-orders?hl=en",
    "title": "When I insert orders to the routines in the Google assistant, he does not do the orders.",
    "content": "When I enter a command to the Google assistant in the routines he does not do it.\nHe do only the set up actions\nFor example I can't insert into the assistant routines like turn on wifi, turn on airplane mode",
    "is_img": 0,
    "category": "Google Assistant and Voice Actions, Google Pixel 3a",
    "post_time": "2020-05-18T11:43:45.736827+00:00",
    "reply": "1 Reply"
}