{
    "url": "https://support.google.com/pixelphone/thread/22828071/trying-to-figure-out-how-to-recover-my-videos-that-were-sent-to-my-trash-and-the-trash-was-empty?hl=en",
    "title": "Trying to figure out how to recover my videos that were sent to my trash and the trash was empty",
    "content": "I'm trying to recover a video that was sent to me trash and the trash wad accidentally emptied",
    "is_img": 0,
    "category": "Other",
    "post_time": "2019-12-14T14:36:55.636684+00:00",
    "reply": "1 Reply"
}