{
    "url": "https://support.google.com/pixelphone/thread/16630441/sorry-this-is-not-question-but-i-have-idea-that-may-help-google-pixel-more-develop-and-futuristic?hl=en",
    "title": "Sorry, this is not question, but i have idea that may help google pixel more develop and futuristic",
    "content": "Sorry, this is not a question, but i have idea that may help google pixel more develop and futuristic. You can contact me for free if you want to know my idea for google pixel, my email is rafaeljustinwijaya@gmail.com. i hope that google respond my opinion and my idea. Last thing, this idea may help people so much when they walk indoor or outdoor",
    "is_img": 0,
    "category": "Other, Google Pixel",
    "post_time": "2019-10-12T12:14:53.407853+00:00",
    "reply": "1 Recommended Answer"
}