{
    "url": "https://support.google.com/pixelphone/thread/85638940/when-i-plug-in-my-phone-the-battery-icon-doesn-t-change-what-should-i-do?hl=en",
    "title": "When I plug in my phone, the battery icon doesn't change. What should I do?",
    "content": "When I plug in my phone to charge, the battery icon does not change. I tested the charger on my mom's phone and it worked for her, so I think the problem is with my phone, which I purchased through Amazon. What should I do?",
    "is_img": 0,
    "category": "Battery and Power, Google Pixel",
    "post_time": "2020-11-27T23:44:05.82872+00:00",
    "reply": "1 Reply"
}