{
    "url": "https://support.google.com/pixelphone/thread/1240284/phone-will-restart-and-load-google-start-screen-and-then-crash-does-this-continuously?hl=en",
    "title": "Phone will restart and load \"GOOGLE\" start screen and then crash. Does this continuously.",
    "content": "I have attempted to hard reset the phone, but the phone will not even register that I am trying this. While plugged up it has a continuous loop of loading the GOOGLE start screen. Nothing else.",
    "is_img": 0,
    "category": "Device Performance, Google Pixel 3 XL",
    "post_time": "2019-01-23T19:51:39.951215+00:00",
    "reply": "2 Replies"
}