{
    "url": "https://support.google.com/pixelphone/thread/80035599/when-my-phone-rings-that-answer-screen-does-not-pop-up-and-i-have-tosearch-to-answer-it?hl=en",
    "title": "When my phone rings that answer screen does not pop up and I have tosearch to answer it.",
    "content": "When my phone rings the answer screen does not pop up. I have to pull down the notification bar and search through the notifications to answer a call.",
    "is_img": 0,
    "category": "Contacts, Calls, Voicemail, Google Pixel 3 XL",
    "post_time": "2020-10-30T16:39:55.482909+00:00",
    "reply": "0 Replies"
}