{
    "url": "https://support.google.com/pixelphone/thread/9722309/sometimes-the-service-of-the-feature-now-playing-isnt-working-do-you-know-the-reason?hl=en",
    "title": "Sometimes the service of the feature \"now playing\" isnt working, do you know the reason?",
    "content": "The feature of Google \"now playing\" isn't working as I wish, the feature sometimes stop making its process! I'm listening to music and doesn't recognize it :(",
    "is_img": 0,
    "category": "Device Performance, Google Pixel 2",
    "post_time": "2019-07-12T02:01:40.451819+00:00",
    "reply": "1 Reply"
}