{
    "url": "https://support.google.com/pixelphone/thread/40486812/chrome-tab-shared-from-mac-to-pixel-2-won-t-load?hl=en",
    "title": "Chrome tab shared from Mac to Pixel 2 won't load",
    "content": "Hey all,\n\nI can send chrome tabs from my Pixel 2's chrome browser to my Mac and open it with no issue, but when I try to send from my Mac to my Pixel, I can't open it. The prompt shows with the link, but when I tap it, nothing happens. Has anyone else encountered this? Is there a fix?",
    "is_img": 0,
    "category": "Other, Google Pixel 2",
    "post_time": "2020-04-16T18:37:14.091818+00:00",
    "reply": "3 Replies"
}