{
    "url": "https://support.google.com/pixelphone/thread/13958900/has-google-managed-to-resolve-the-soft-mesh-speaker-design-flaw-for-any-other-users?hl=en",
    "title": "Has Google managed to resolve the soft mesh speaker design flaw for any other users?",
    "content": "Had my Google Pixel 3 for a couple months now and I tried to clean some dirt from the speaker and found out the mesh is very soft and has become dented. Checking online and I've found other users with the same problem. Any way for Google to resolve this?",
    "is_img": 0,
    "category": "Other, Google Pixel 3",
    "post_time": "2019-09-09T15:56:58.283809+00:00",
    "reply": "3 Replies"
}