{
    "url": "https://support.google.com/pixelphone/thread/52850802/pixel-3axl-stopped-sending-texts-won-t-resend-turned-on-off-cleared-cache-forcedstop-any-ideas?hl=en",
    "title": "Pixel 3axl stopped sending texts-won't resend. Turned on/off, cleared cache, forcedstop any ideas?",
    "content": "Turned on/off, cleared cache, force stopped but texts won't send.  Fine Intel an hour or so ago...",
    "is_img": 0,
    "category": "Device Performance, Google Pixel 3a XL",
    "post_time": "2020-06-11T16:38:53.696482+00:00",
    "reply": "1 Reply"
}