{
    "url": "https://support.google.com/pixelphone/thread/3547309/my-pixel-3-wont-start-displaying-cant-find-a-valid-operating-system?hl=en",
    "title": "My pixel 3 wont start, displaying cant find a valid operating system!",
    "content": "My pixel 3 suddenly started to display a message stating \"  cant find a valid operating system, Device wont start\"",
    "is_img": 0,
    "category": "Device Performance, Google Pixel 3",
    "post_time": "2019-04-04T05:38:47.791428+00:00",
    "reply": "4 Replies"
}