{
    "url": "https://support.google.com/pixelphone/thread/7108325/my-volume-rocker-had-become-loose-and-out-of-place?hl=en",
    "title": "My volume rocker had become loose and out of place.",
    "content": "My volume Up rocker now had been out of its place. So worried that this may impact the water ressistant of the phone. can i send for RMA",
    "is_img": 1,
    "category": "Device Performance, Google Pixel 3",
    "post_time": "2019-05-31T01:04:15.881019+00:00",
    "reply": "1 Recommended Answer"
}