{
    "url": "https://support.google.com/pixelphone/thread/17978236/pixel-2-is-stuck-at-google-screen-tried-with-safe-mode-recovery-mode-wipe-data-factory-reset?hl=en",
    "title": "Pixel 2 is stuck at Google screen. Tried with safe mode, recovery mode(Wipe data/factory reset)",
    "content": "My Pixel 2 got powered off 2 days back and it was not turning on. Later, tried with safe mode and Data wipe/recovery mode as well. Even that did not help.\n\nRight now, I can see Google screen and it is stuck there. Tried factory reset multiple times.\n\nPls help if anyone know a way out.",
    "is_img": 0,
    "category": "Other, Google Pixel 2",
    "post_time": "2019-10-29T05:06:56.206083+00:00",
    "reply": "0 Replies"
}