{
    "url": "https://support.google.com/pixelphone/thread/4101110/pixel-phone-not-recognizing-sim?hl=en",
    "title": "Pixel phone not recognizing SIM",
    "content": "I just got a new Pixel 3 phone and it will not recognise the SIM card. I have tried installing all updates, a different SIM, and restarting the phone all to no avail. My SIM works in all other phones that I have, but not the Pixel.\n\nPlease help",
    "is_img": 0,
    "category": "Setting up and Personalizing your Device, Google Pixel 3",
    "post_time": "2019-04-13T13:39:39.880417+00:00",
    "reply": "1 Recommended Answer"
}