{
    "url": "https://support.google.com/pixelphone/thread/39395526/can-my-frozen-pixel-4xl-be-fixed-without-taking-it-in-for-repairs?hl=en",
    "title": "Can my frozen pixel 4XL be fixed without taking it in for repairs?",
    "content": "I've tried resetting it numerous times. Did all the resets. Still frozen.. I really don't have the extra money to get it repaired right now. (especially wit this virus goin around) Was asking for help.",
    "is_img": 0,
    "category": "Device Performance, Google Pixel 4 XL",
    "post_time": "2020-04-11T14:04:21.670636+00:00",
    "reply": "1 Reply"
}