{
    "url": "https://support.google.com/pixelphone/thread/77302607/i-wanna-buy-pixel-4a-5g-but-you-guys-haven-t-launched-it-in-india-why?hl=en",
    "title": "I wanna buy pixel 4a 5G but you guys haven't launched it in India ? Why ????????",
    "content": "Tried contacting each n every one who works at google , please please launch both the pixel phones in india that are not launched in India",
    "is_img": 0,
    "category": "Other",
    "post_time": "2020-10-16T12:00:26.041058+00:00",
    "reply": "1 Reply"
}