{
    "url": "https://support.google.com/pixelphone/thread/35204317/music-keeps-playing-in-pixel-3-when-i-am-getting-call-in-vibrate-mode-how-to-fix-it?hl=en",
    "title": "Music keeps playing in pixel 3 when I am getting call in vibrate mode? How to fix it?",
    "content": "I am having some problem; While I am playing music be it amazon prime or youtube, when I get calls in vibrate mode the music won't pause. I receive call and vibrate for call due to which I don't even know I had missed calls. Why is that happening? My device is Pixel 3. My wife has Pixel 4 but same problem. Looks like unwanted feature. How to fix it?",
    "is_img": 0,
    "category": "Device Performance, Google Pixel 3",
    "post_time": "2020-03-23T21:19:10.720942+00:00",
    "reply": "2 Replies"
}