{
    "url": "https://support.google.com/pixelphone/thread/70326212/updated-applications-from-google-play-store-this-morning-and-now-my-phone-is-giving-problem?hl=en",
    "title": "Updated applications from Google play store this morning and now my phone is giving problem.",
    "content": "Updated applications from Google play store this morning, now my phone is giving problem. Like i click update all. Me and brother we are using Vodafone sim card, he is getting network but i am not. And when i tried to open play store, it just shows the Google play store logo on my phone.",
    "is_img": 0,
    "category": "Connectivity, Network, Bluetooth, Google Pixel 3a",
    "post_time": "2020-09-10T17:14:46.161824+00:00",
    "reply": "1 Recommended Answer"
}