{
    "url": "https://support.google.com/pixelphone/thread/5482382/i-have-issues-with-the-4g-network-dropping-out-constantly-on-my-2xl-i-am-with-telstra-au?hl=en",
    "title": "I have issues with the 4g network dropping out constantly on my 2xl I am with Telstra Au.",
    "content": "Have tried all the obvious things turned airplane on and off restarted phone. Resorted to 3g which works for calls but should not have to use 3g on this phone",
    "is_img": 0,
    "category": "Connectivity, Network, Bluetooth, Google Pixel 2",
    "post_time": "2019-05-04T22:21:36.042525+00:00",
    "reply": "2 Replies"
}