{
    "url": "https://support.google.com/pixelphone/thread/74915531/sound-is-not-working-on-my-pixel-3a-i-am-talking-about-all-sound-here-media-button-pressing-etc?hl=en",
    "title": "Sound is not working on my Pixel 3a. I am talking about all sound here( media, button pressing etc).",
    "content": "The sound only returns when I restart the phone, but the issue seems to occur more and more often. This only started happening after I downloaded Android 11. It makes no difference whether I am using earphones or not.",
    "is_img": 0,
    "category": "Device Performance, Google Pixel 3a",
    "post_time": "2020-10-04T18:27:16.814256+00:00",
    "reply": "0 Replies"
}