{
    "url": "https://support.google.com/pixelphone/thread/9443312/pixel-3-xl-can-t-find-valid-operating-system?hl=en",
    "title": "Pixel 3 XL Can't find Valid Operating System",
    "content": "Hi\nAfter signing up for the beta program and downloading beta 4 by OTA, my device does not start and show me:\n\"Can't find valid operating system. The device will not start.\"\nThen shows the visit g.co/ABH link.\n\nI am not even able to boot into recovery. When selecting recovery from fastboot mode it just goes right to the same \"Can't find valid operating system...\" screen.\n\nDevice State: Locked\nDeveloper Mode : Not Enabled and not possible to do now\n\n\nPLease help me. As i am from Chile , there is nothing i can't claim for warranty.",
    "is_img": 0,
    "category": "Other, Google Pixel 3 XL",
    "post_time": "2019-07-07T19:23:16.86473+00:00",
    "reply": "1 Recommended Answer"
}