{
    "url": "https://support.google.com/pixelphone/thread/93988060/phone-favourites-balloons?hl=en",
    "title": "Phone favourites balloons",
    "content": "Can you get the favourites to show as a list? At the moment they are showing with balloons (photos, I suppose, if the contact had them) and they are in no particular order which makes the list pretty useless.",
    "is_img": 0,
    "category": "Setting up and Personalizing your Device, Google Pixel 4a",
    "post_time": "2021-01-18T11:12:19.971409+00:00",
    "reply": "1 Recommended Answer"
}