{
    "url": "https://support.google.com/pixelphone/thread/11893566/why-does-google-assistant-not-pick-up-my-voice-when-using-bluetooth-and-squeeze-feature?hl=en",
    "title": "Why does Google assistant not pick up my voice when using Bluetooth and squeeze feature?",
    "content": "When I'm connected to my car Bluetooth and i squeeze to open Google assistant, it says it's listening but doesn't actually pick up anything I tell it. However if I use ok Google feature while using the Bluetooth it does hear me. Why?",
    "is_img": 0,
    "category": "Connectivity, Network, Bluetooth, Google Pixel 2",
    "post_time": "2019-08-13T11:31:44.529643+00:00",
    "reply": "5 Replies"
}