{
    "url": "https://support.google.com/pixelphone/thread/57833449/how-do-i-get-back-into-my-account-it-keeps-saying-it-s-not-me-not-enough-information-to-verify?hl=en",
    "title": "How do I get back into my account. It keeps saying it's not me. Not enough information to verify.",
    "content": "I'm trying to reset my password and it keeps sending me around in circles saying there's not enough information that can't verify that it's me..",
    "is_img": 0,
    "category": "Other, Google Pixel 2",
    "post_time": "2020-07-08T16:33:26.417129+00:00",
    "reply": "1 Reply"
}