{
    "url": "https://support.google.com/pixelphone/thread/27103322/my-pixel-2-camera-stopped-working-out-of-nowhere?hl=en",
    "title": "My pixel 2 camera stopped working out of nowhere",
    "content": "My camera is not working i have tried everything including rolling back to older version. I cannot take it to google store as I live in pakistan and there is no google store here. Please help me as i just bought the phone second hand",
    "is_img": 0,
    "category": "Camera, Google Pixel 2",
    "post_time": "2020-01-29T23:09:40.464446+00:00",
    "reply": "1 Reply"
}