{
    "url": "https://support.google.com/pixelphone/thread/1589535/i-used-to-be-able-to-select-a-person-and-see-in-and-out-calls-for-that-one-not-just-daily-histories?hl=en",
    "title": "I used to be able to select a person and see in and out calls for that one, not just daily histories",
    "content": "How can I see an individual's history instead of just general call history that I would have to scroll through to find all calls.",
    "is_img": 0,
    "category": "Contacts, Calls, Voicemail, Google Pixel 3",
    "post_time": "2019-02-11T22:11:56.590129+00:00",
    "reply": "1 Reply"
}