{
    "url": "https://support.google.com/pixelphone/thread/1744820/pixel-3-people-have-difficulty-hearing-me-pixel-buds-seem-to-help-whats-wrong-with-phone-mic?hl=en",
    "title": "Pixel 3 - people have difficulty hearing me. Pixel Buds seem to help. Whats wrong with phone mic ?",
    "content": "People have difficult hearing me when using the phone mic, but can hear me ok with Pixel Buds",
    "is_img": 0,
    "category": "Contacts, Calls, Voicemail, Google Pixel 3 XL",
    "post_time": "2019-02-19T21:06:15.429599+00:00",
    "reply": "0 Replies"
}