{
    "url": "https://support.google.com/pixelphone/thread/91546417/looking-for-a-compatable-qi-receiver-for-the-pixel-4a?hl=en",
    "title": "Looking for a compatable qi receiver for the pixel 4a.",
    "content": "Is there a qi receiver that will work with the 4a? I tried the 1amp qi and it did not work. Any suggestions for a higher amp receiver?",
    "is_img": 0,
    "category": "Battery and Power, Google Pixel 4a",
    "post_time": "2021-01-01T17:58:59.584267+00:00",
    "reply": "0 Replies"
}