{
    "url": "https://support.google.com/pixelphone/thread/106699789/battery-not-charging-sometimes?hl=en",
    "title": "Battery not charging...sometimes",
    "content": "Sometimes my pixel 4a 5G doesn't charge. I have to turn it off the get it to start charging. I've tried turning adaptive charging/battery on and off but it makes no difference. I've tried changing cables and adapters, yet it's still the same result.",
    "is_img": 0,
    "category": "Battery and Power, Google Pixel 4a (5G)",
    "post_time": "2021-04-19T00:22:03.16541+00:00",
    "reply": "1 Recommended Answer"
}