{
    "url": "https://support.google.com/pixelphone/thread/101214886/why-is-the-screen-on-my-google-pixel-3a-has-been-playing-up?hl=en",
    "title": "Why is the screen on my Google pixel 3a has been playing up?",
    "content": "I'm trying to prevent my phone from playing up the way that it has. The screen would go almost white and faint lines would appear that flicker. So far it eventually would said but I want it to stop from happening all together. I've tried restarting my phone but that didn't work.",
    "is_img": 0,
    "category": "Device Performance, Google Pixel 3a",
    "post_time": "2021-03-07T23:10:01.809769+00:00",
    "reply": "1 Reply"
}