{
    "url": "https://support.google.com/pixelphone/thread/76415409/trying-to-access-google-play-but-its-signed-in-as-someone-else-how-do-i-switch-user-its-not-an-opti?hl=en",
    "title": "Trying to access google play but its signed in as someone else. How do I switch user-its not an opti",
    "content": "I'm borrowing a Samsung A8. I have signed into my google account, but when I try to access google play, it only gives me the option to sign in as my mate who owns the phone-it doesn't give me an option to sign in with a different user/account. I don't want to delete his account though I will give the phone back",
    "is_img": 0,
    "category": "Setting up and Personalizing your Device, Google Pixel",
    "post_time": "2020-10-12T06:09:55.40949+00:00",
    "reply": "0 Replies"
}