{
    "url": "https://support.google.com/pixelphone/thread/104137279/i-have-a-pixel-4a-and-barely-touch-4-hrs-of-sot-i-don-t-know-what-s-the-issue-with-it?hl=en",
    "title": "I have a pixel 4a and barely touch 4 hrs of SOT. I don't know what's the issue with it.",
    "content": "I have only minimal apps installed and this is getting really serious!",
    "is_img": 0,
    "category": "Battery and Power, Google Pixel 4a",
    "post_time": "2021-03-28T02:47:01.2891+00:00",
    "reply": "11 Replies"
}