{
    "url": "https://support.google.com/pixelphone/thread/21962917/bluetooth-connections-dropping-since-dec-2019-update-for-pixel-3-next-step?hl=en",
    "title": "Bluetooth connections dropping since Dec 2019 update for Pixel 3, next step?",
    "content": "My device is dropping Bluetooth connections randomly and not connecting to previously paired devices since the December 2019 update",
    "is_img": 0,
    "category": "Connectivity, Network, Bluetooth, Google Pixel 3",
    "post_time": "2019-12-04T23:34:31.889697+00:00",
    "reply": "10 Replies"
}